diamondoracle/__init__.py
diamondoracle/cardmeanings.py
diamondoracle/clear.py
diamondoracle/datelog.py
diamondoracle/main.py
diamondoracle/onecard.py
haileysdiamond-0.0.3.dist-info/LICENSE
haileysdiamond-0.0.3.dist-info/METADATA
haileysdiamond-0.0.3.dist-info/WHEEL
haileysdiamond-0.0.3.dist-info/top_level.txt
haileysdiamond-0.0.3.dist-info/RECORD
