Metadata-Version: 2.1
Name: haileysdiamond
Version: 0.0.3
Summary: Hiley's Diamond Oracle
Home-page: https://github.com/pypa/sampleproject
Author: Jake
Author-email: jsrowell55@gmail.com
Project-URL: Bug Tracker, https://github.com/pypa/sampleproject/issues
Classifier: Programming Language :: Python :: 3
Classifier: License :: OSI Approved :: MIT License
Classifier: Operating System :: OS Independent
Requires-Python: >=3.6
License-File: LICENSE
